{
  "star_fall": {
    "sounds": [
      {
        "name": "zeldacraft:star_fall",
        "stream": true
      }
    ]
  },

  "emeraldshardpickedup": {
    "sounds": [
      "zeldacraft:emerald_shard_picked_up"
    ]
  },
  "starpickedup": {
    "sounds": [
      "zeldacraft:star_pickup"
    ]
  },
  "star_used": {
    "sounds": [
      "zeldacraft:star_used"
    ]
  },
  "falling_star": {
    "subtitle": "sounds.zeldacraft.falling_star",
    "sounds": [
      {
        "name": "zeldacraft:falling_star",
        "attenuation_distance": 100
      }
    ]
  },

  "transform": {
    "sounds": [
      "zeldacraft:transform"
    ]
  },

  "upgrade_mana": {
    "sounds": [
      "zeldacraft:upgrade_mana"
    ]
  },
  "no_mana": {
    "sounds": [
      "zeldacraft:no_mana"
    ]
  },


  "fire_magic": {
    "subtitle": "sounds.zeldacraft.fire_magic",
    "sounds": [
      "zeldacraft:fire_magic"
    ]
  },
  "ice_magic": {
    "subtitle": "sounds.zeldacraft.ice_magic",
    "sounds": [
      "zeldacraft:ice_magic"
    ]
  },
  "beam_magic": {
    "subtitle": "sounds.zeldacraft.beam_magic",
    "sounds": [
      "zeldacraft:beam_magic"
    ]
  },


  "musicdisclegend": {
    "sounds": [
      "zeldacraft:music_disc_legend"
    ]
  },

  "powerup": {
    "sounds": [
      "zeldacraft:powerup"
    ]
  },


  "swordshoot": {
    "subtitle": "sounds.zeldacraft.sword_shoot",
    "sounds": [
      "zeldacraft:sword_shoot"
    ]
  },
  "swordrecharge": {
    "sounds": [
      "zeldacraft:sword_recharge"
    ]
  },
  "smaaash_sound": {
    "sounds": [
      "zeldacraft:smaaash_sound"
    ]
  },


  "secretroom": {
    "sounds": [
      "zeldacraft:secret"
    ]
  },


  "fairy_ambient": {
    "subtitle": "sounds.zeldacraft.fairy_ambient",
    "sounds": [
      "zeldacraft:fairy_ambient"
    ]
  },
  "fairy_hurt": {
    "subtitle": "sounds.zeldacraft.fairy_hurt",
    "sounds": [
      "zeldacraft:fairy_hurt"
    ]
  },
  "fairy_death": {
    "subtitle": "sounds.zeldacraft.fairy_death",
    "sounds": [
      "zeldacraft:fairy_death"
    ]
  },
  "fairy_in": {
    "subtitle": "sounds.zeldacraft.fairy_in",
    "sounds": [
      "zeldacraft:navi_in"
    ]
  },
  "fairy_out": {
    "subtitle": "sounds.zeldacraft.fairy_out",
    "sounds": [
      "zeldacraft:navi_out"
    ]
  },
  "navi_hello": {
    "subtitle": "sounds.zeldacraft.navi_hello",
    "sounds": [
      "zeldacraft:navi_hello",
      "zeldacraft:navi_hey"
    ]
  },
  "navi_attention": {
    "subtitle": "sounds.zeldacraft.navi_attention",
    "sounds": [
      "zeldacraft:navi_hey",
      "zeldacraft:navi_listen",
      "zeldacraft:navi_look",
      "zeldacraft:navi_watchout"
    ]
  },
  "tatl_in": {
    "subtitle": "sounds.zeldacraft.fairy_in",
    "sounds": [
      "zeldacraft:tatl_in"
    ]
  },
  "tatl_out": {
    "subtitle": "sounds.zeldacraft.fairy_out",
    "sounds": [
      "zeldacraft:tatl_out"
    ]
  },
  "tatl_attention": {
    "subtitle": "sounds.zeldacraft.tatl_attention",
    "sounds": [
      "zeldacraft:tatl_hey",
      "zeldacraft:tatl_listen",
      "zeldacraft:tatl_alarm"
    ]
  },
  "tatl_sad": {
    "subtitle": "sounds.zeldacraft.tatl_sad",
    "sounds": [
      "zeldacraft:tatl_sad"
    ]
  },
  "tatl_bell_sound": {
    "subtitle": "sounds.zeldacraft.tatl_hello",
    "sounds": [
      "zeldacraft:tatl_hey",
      "zeldacraft:tatl_listen"
    ]
  },

  "hookshot_active": {
    "subtitle": "sounds.zeldacraft.hookshot_active",
    "sounds": [
      "zeldacraft:hookshot_active"
    ]
  },

  "boomerang_in_air": {
    "subtitle": "sounds.zeldacraft.boomerang_in_air",
    "sounds": [
      "zeldacraft:boomerang_in_air"
    ]
  },
  "boomerang_caught": {
    "subtitle": "sounds.zeldacraft.boomerang_caught",
    "sounds": [
      "zeldacraft:boomerang_caught"
    ]
  },


  "tektite_hurt": {
    "subtitle": "sounds.zeldacraft.tektite_hurt",
    "sounds": [
      "zeldacraft:tektite_hurt"
    ]
  },
  "tektite_death": {
    "subtitle": "sounds.zeldacraft.tektite_death",
    "sounds": [
      "zeldacraft:tektite_death"
    ]
  },

  "dungeon_door_open": {
    "subtitle": "subtitles.block.door.toggle",
    "sounds": [
      "zeldacraft:dungeon_door_open"
    ]
  },
  "dungeon_door_close": {
    "subtitle": "subtitles.block.door.toggle",
    "sounds": [
      "zeldacraft:dungeon_door_close"
    ]
  },

  "zelda_advancement_reg": {
    "sounds": [
      "zeldacraft:zeldaadvancement"
    ]
  },

  "zelda_advancement_goal": {
    "sounds": [
      "zeldacraft:zeldagoal"
    ]
  }
}