{
  "type": "minecraft:chest",
  "pools": [
    {
      "rolls": 1,
      "entries": [
        {
          "type": "minecraft:item",
          "name": "zeldacraft:emerald_shard",
          "weight": 150
        },
        {
          "type": "minecraft:item",
          "name": "minecraft:arrow",
          "weight": 150
        },
        {
          "type": "minecraft:item",
          "name": "minecraft:spectral_arrow",
          "weight": 50
        },
        {
          "type": "minecraft:item",
          "name": "minecraft:emerald",
          "weight": 50
        },
        {
          "type": "minecraft:item",
          "name": "zeldacraft:bomb",
          "weight": 25
        },
        {
          "type": "minecraft:item",
          "name": "zeldacraft:magic_jar",
          "weight": 25
        },
        {
          "type": "minecraft:item",
          "name": "zeldacraft:bombchu",
          "weight": 15
        },
        {
          "type": "minecraft:item",
          "name": "zeldacraft:music_disc_legend_fragment",
          "weight": 10
        },
        {
          "type": "minecraft:item",
          "name": "zeldacraft:stardust",
          "weight": 2
        }
      ]
    }
  ]
}
